{
    "entities": {
        "items": [],
        "locations": [],
        "characters": [],
        "attribs": [],
        "events": []
    },
    "general data": {
        "piles": []
    },
    "progress": [],
    "overall settings": {
        "description": "Under *Main Setup* (shortcut key **M**), browse the *Pre-built Scenarios*. Or, continue a previously saved game by clicking *Upload*.\r\n\r\nTo start from scratch, go to *Scenario Settings* and describe your idea, along with a title. Next, add a few initial items or characters. More can be set up as the game goes along. Your AI can provide lists of choices like a tabletop manual, or use it to add details such as a real-world description of iron.",
        "number_format": "en_US",
        "slots": [],
        "title": "Generic Adventure",
        "win_reqs": [],
        "tag_introduce_order": 50,
        "tag_best_order": 50,
        "tag_progress_type": "?",
        "tag_multiplayer": false,
        "tag_complete": "02 Under Construction"
    }
}
